electricpy/__init__.py
electricpy/bode.py
electricpy/compute.py
electricpy/constants.py
electricpy/conversions.py
electricpy/fault.py
electricpy/latex.py
electricpy/machines.py
electricpy/math.py
electricpy/passive.py
electricpy/phasors.py
electricpy/sim.py
electricpy/thermal.py
electricpy/version.py
electricpy/visu.py
electricpy/active/__init__.py
electricpy/geometry/__init__.py
electricpy/geometry/circle.py
electricpy/geometry/triangle.py
electricpy-0.3.0.dist-info/LICENSE
electricpy-0.3.0.dist-info/WHEEL
electricpy-0.3.0.dist-info/METADATA
electricpy-0.3.0.dist-info/RECORD
