Metadata-Version: 2.1
Name: electricpy
Version: 0.3.0
Summary: Electrical Engineering Functions in Python
Author: Lakshmikanth Ayyadevara, Miguel Zabala, I Wayan Kurniawan, Tanvir Riyad
Author-email: Joe Stanley <engineerjoe440@yahoo.com>, Khan Asfi Reza <khanasfireza10@gmail.com>, Arthur Lorencini Bergamaschi <arthur.lorencini@gmail.com>, Soham Ratnaparkhi <soham.ratnaparkhi@gmail.com>, Ankush <ankush.opensource@gmail.com>
Maintainer-email: Joe Stanley <engineerjoe440@yahoo.com>
Requires-Python: >=3.7
Classifier: Programming Language :: Python :: 3
Classifier: License :: OSI Approved :: MIT License
Classifier: Operating System :: OS Independent
Requires-Dist: NumPy
Requires-Dist: matplotlib
Requires-Dist: SciPy
Requires-Dist: SymPy
Requires-Dist: numdifftools
Requires-Dist: arcflash ; extra == "fault"
Requires-Dist: numdifftools ; extra == "full"
Requires-Dist: arcflash ; extra == "full"
Requires-Dist: numdifftools ; extra == "numerical"
Project-URL: Documentation, https://electricpy.readthedocs.io/en/latest/
Project-URL: Home, https://electricpy.readthedocs.io/en/latest/index.html
Project-URL: Issues, https://github.com/engineerjoe440/ElectricPy/issues
Project-URL: Repository, https://github.com/engineerjoe440/ElectricPy
Provides-Extra: fault
Provides-Extra: full
Provides-Extra: numerical
